<PrefabDef>
  <defName>Prefab_20251231_222152</defName>
  <size>(27,21)</size>
  <extraInfo>
    <version>1.6.9438.37837</version>
    <name>原始家</name>
    <description></description>
    <tags>
      <li>FullExport</li>
    </tags>
    <author></author>
    <category>宿舍</category>
    <BuildingID>0ddde395-f9cd-4d9e-acde-c75231289450</BuildingID>
    <modPackages>
      <mod>
        <packageId>aoba.fortress.industrial.concrete</packageId>
        <name>Industrial concrete</name>
        <version></version>
        <modorder>44</modorder>
        <steamWorkshopId>2888037450</steamWorkshopId>
        <things>
          <li>IC_PortableConcrete</li>
          <li>FT_BlocksConcrete</li>
        </things>
      </mod>
      <mod>
        <packageId>ludeon.rimworld.royalty</packageId>
        <name>Royalty</name>
        <version></version>
        <modorder>2</modorder>
        <things>
          <li>MeditationSpot</li>
          <li>Mote_PsyfocusPulse</li>
        </things>
      </mod>
      <mod>
        <packageId>ludeon.rimworld.odyssey</packageId>
        <name>Odyssey</name>
        <version></version>
        <modorder>5</modorder>
        <things>
          <li>ShallowFloodwater</li>
        </things>
      </mod>
      <mod>
        <packageId>ludeon.rimworld</packageId>
        <name>Core</name>
        <version></version>
        <modorder>1</modorder>
        <things></things>
      </mod>
      <mod>
        <packageId>nals.facialanimation</packageId>
        <name>[NL] Facial Animation - WIP</name>
        <version></version>
        <modorder>10</modorder>
        <steamWorkshopId>1635901197</steamWorkshopId>
        <things></things>
      </mod>
      <mod>
        <packageId>ludeon.rimworld.biotech</packageId>
        <name>Biotech</name>
        <version></version>
        <modorder>3</modorder>
        <things></things>
      </mod>
      <mod>
        <packageId>jintuzilamian.hairstyle.afumenshairstyles</packageId>
        <name><![CDATA[AFU男士发型_Men's hairstyles]]></name>
        <version></version>
        <modorder>17</modorder>
        <steamWorkshopId>3626568306</steamWorkshopId>
        <things></things>
      </mod>
      <mod>
        <packageId>co.uk.epicguru.meleeanimation</packageId>
        <name>Melee Animation</name>
        <version></version>
        <modorder>27</modorder>
        <steamWorkshopId>2944488802</steamWorkshopId>
        <dependencies>
          <li>
            <packageId>brrainz.harmony</packageId>
            <steamWorkshopId>2009463077</steamWorkshopId>
          </li>
        </dependencies>
        <things></things>
      </mod>
    </modPackages>
    <multiLanguage>
      <name>
        <default>原始家</default>
        <zh-CN>原始家</zh-CN>
      </name>
    </multiLanguage>
  </extraInfo>
  <things>
    <TrapSpike>
      <rects>
        <li>(0,0,0,0)</li>
        <li>(2,0,2,0)</li>
        <li>(4,0,4,0)</li>
        <li>(6,0,6,0)</li>
        <li>(8,0,8,0)</li>
        <li>(10,0,10,0)</li>
        <li>(12,0,12,0)</li>
        <li>(14,0,14,0)</li>
        <li>(16,0,16,0)</li>
        <li>(18,0,18,0)</li>
        <li>(20,0,20,0)</li>
        <li>(22,0,22,0)</li>
        <li>(24,0,24,0)</li>
        <li>(26,0,26,0)</li>
        <li>(0,20,0,20)</li>
        <li>(2,20,2,20)</li>
        <li>(4,20,4,20)</li>
        <li>(6,20,6,20)</li>
        <li>(8,20,8,20)</li>
        <li>(10,20,10,20)</li>
        <li>(12,20,12,20)</li>
        <li>(14,20,14,20)</li>
        <li>(16,20,16,20)</li>
        <li>(18,20,18,20)</li>
        <li>(20,20,20,20)</li>
        <li>(22,20,22,20)</li>
        <li>(24,20,24,20)</li>
        <li>(26,20,26,20)</li>
      </rects>
      <stuff>WoodLog</stuff>
      <hp>26</hp>
      <color>RGBA(0.522, 0.380, 0.263, 1.000)</color>
    </TrapSpike>
    <Plant_Bush>
      <rects>
        <li>(9,0,9,0)</li>
      </rects>
      <hp>120</hp>
    </Plant_Bush>
    <Plant_TreePoplar>
      <rects>
        <li>(19,0,19,0)</li>
      </rects>
      <hp>200</hp>
    </Plant_TreePoplar>
    <Filth_RubbleRock>
      <rects>
        <li>(20,0,20,0)</li>
        <li>(18,20,18,20)</li>
      </rects>
    </Filth_RubbleRock>
    <ChunkGranite>
      <rects>
        <li>(21,0,21,0)</li>
        <li>(22,14,22,14)</li>
        <li>(21,15,21,15)</li>
        <li>(17,18,17,18)</li>
        <li>(20,20,20,20)</li>
      </rects>
      <relativeRotation>Clockwise</relativeRotation>
      <hp>300</hp>
      <color>RGBA(0.412, 0.373, 0.380, 1.000)</color>
    </ChunkGranite>
    <Wall>
      <rects>
        <li>(0,1,26,1)</li>
        <li>(0,2,1,2)</li>
        <li>(9,2,9,3)</li>
        <li>(25,2,26,2)</li>
        <li>(0,3,0,8)</li>
        <li>(26,3,26,8)</li>
        <li>(1,8,1,8)</li>
        <li>(25,8,25,8)</li>
        <li>(0,10,1,10)</li>
        <li>(25,10,26,10)</li>
        <li>(0,11,0,19)</li>
        <li>(26,11,26,19)</li>
        <li>(9,17,9,19)</li>
        <li>(1,18,1,19)</li>
        <li>(25,18,25,19)</li>
        <li>(2,19,8,19)</li>
        <li>(10,19,24,19)</li>
      </rects>
      <stuff>Steel</stuff>
      <hp>300</hp>
      <color>RGBA(0.412, 0.412, 0.412, 1.000)</color>
    </Wall>
    <Bed>
      <position>(24, 0, 2)</position>
      <relativeRotation>Counterclockwise</relativeRotation>
      <stuff>WoodLog</stuff>
      <quality>Normal</quality>
      <hp>91</hp>
      <color>RGBA(0.522, 0.380, 0.263, 1.000)</color>
    </Bed>
    <Filth_Dirt>
      <rects>
        <li>(3,3,3,3)</li>
        <li>(5,3,6,3)</li>
        <li>(2,4,2,14)</li>
        <li>(13,5,13,5)</li>
        <li>(5,8,5,9)</li>
        <li>(8,8,8,9)</li>
        <li>(10,8,10,9)</li>
        <li>(0,9,1,9)</li>
        <li>(3,9,4,9)</li>
        <li>(6,9,7,9)</li>
        <li>(9,9,9,9)</li>
        <li>(11,9,15,9)</li>
        <li>(18,9,18,9)</li>
        <li>(23,9,26,9)</li>
        <li>(6,10,6,12)</li>
        <li>(12,10,12,11)</li>
        <li>(11,11,11,11)</li>
        <li>(17,11,19,11)</li>
        <li>(24,11,24,12)</li>
        <li>(13,12,13,12)</li>
        <li>(17,12,17,12)</li>
        <li>(25,12,25,14)</li>
        <li>(4,13,4,14)</li>
        <li>(10,13,12,13)</li>
        <li>(14,13,14,13)</li>
        <li>(18,13,18,14)</li>
        <li>(21,13,21,13)</li>
        <li>(24,16,25,16)</li>
        <li>(13,17,13,17)</li>
        <li>(6,18,6,18)</li>
        <li>(14,18,14,18)</li>
        <li>(16,18,16,18)</li>
      </rects>
      <color>RGBA(0.357, 0.294, 0.255, 0.380)</color>
    </Filth_Dirt>
    <Filth_AnimalFilth>
      <rects>
        <li>(3,3,4,3)</li>
        <li>(24,3,24,3)</li>
        <li>(2,5,2,5)</li>
        <li>(24,7,24,7)</li>
        <li>(2,8,2,8)</li>
        <li>(5,9,6,9)</li>
        <li>(8,9,8,9)</li>
        <li>(10,9,12,9)</li>
        <li>(14,9,14,9)</li>
        <li>(21,9,21,9)</li>
        <li>(24,9,25,9)</li>
        <li>(2,11,2,11)</li>
        <li>(12,11,12,11)</li>
        <li>(18,13,18,13)</li>
        <li>(2,16,2,16)</li>
      </rects>
      <color>RGBA(0.380, 0.255, 0.188, 0.380)</color>
    </Filth_AnimalFilth>
    <Wall>
      <rects>
        <li>(3,4,23,4)</li>
        <li>(3,5,3,8)</li>
        <li>(9,5,9,8)</li>
        <li>(15,5,15,8)</li>
        <li>(23,5,23,8)</li>
        <li>(3,10,5,10)</li>
        <li>(7,10,11,10)</li>
        <li>(13,10,18,10)</li>
        <li>(20,10,23,10)</li>
        <li>(3,11,3,16)</li>
        <li>(9,11,9,16)</li>
        <li>(15,11,15,16)</li>
        <li>(23,11,23,16)</li>
        <li>(5,13,5,16)</li>
        <li>(7,13,7,16)</li>
        <li>(4,16,4,16)</li>
        <li>(6,16,6,16)</li>
        <li>(8,16,8,16)</li>
        <li>(10,16,14,16)</li>
        <li>(16,16,22,16)</li>
      </rects>
      <stuff>WoodLog</stuff>
      <hp>195</hp>
      <color>RGBA(0.522, 0.380, 0.263, 1.000)</color>
    </Wall>
    <TableStonecutter>
      <position>(11, 0, 5)</position>
      <relativeRotation>Opposite</relativeRotation>
      <stuff>WoodLog</stuff>
      <hp>117</hp>
      <color>RGBA(0.522, 0.380, 0.263, 1.000)</color>
    </TableStonecutter>
    <IC_PortableConcrete>
      <position>(14, 0, 6)</position>
      <relativeRotation>Opposite</relativeRotation>
      <hp>180</hp>
    </IC_PortableConcrete>
    <TableButcher>
      <position>(17, 0, 5)</position>
      <relativeRotation>Opposite</relativeRotation>
      <stuff>WoodLog</stuff>
      <hp>117</hp>
      <color>RGBA(0.522, 0.380, 0.263, 1.000)</color>
    </TableButcher>
    <FueledStove>
      <position>(20, 0, 5)</position>
      <relativeRotation>Opposite</relativeRotation>
      <hp>180</hp>
    </FueledStove>
    <ShelfSmall>
      <rects>
        <li>(22,5,22,5)</li>
      </rects>
      <stuff>WoodLog</stuff>
      <hp>32</hp>
      <color>RGBA(0.522, 0.380, 0.263, 1.000)</color>
    </ShelfSmall>
    <MealFine_Veg>
      <rects>
        <li>(22,5,22,5)</li>
      </rects>
      <hp>50</hp>
    </MealFine_Veg>
    <Table2x4c>
      <position>(6, 0, 7)</position>
      <relativeRotation>Clockwise</relativeRotation>
      <stuff>WoodLog</stuff>
      <quality>Good</quality>
      <hp>98</hp>
      <color>RGBA(0.522, 0.380, 0.263, 1.000)</color>
    </Table2x4c>
    <DiningChair>
      <rects>
        <li>(11,6,11,6)</li>
        <li>(20,6,20,6)</li>
        <li>(14,7,14,7)</li>
        <li>(11,8,11,8)</li>
      </rects>
      <relativeRotation>Opposite</relativeRotation>
      <stuff>WoodLog</stuff>
      <quality>Good</quality>
      <hp>65</hp>
      <color>RGBA(0.522, 0.380, 0.263, 1.000)</color>
    </DiningChair>
    <DiningChair>
      <rects>
        <li>(17,6,17,6)</li>
        <li>(5,8,5,8)</li>
      </rects>
      <relativeRotation>Opposite</relativeRotation>
      <stuff>WoodLog</stuff>
      <quality>Normal</quality>
      <hp>65</hp>
      <color>RGBA(0.522, 0.380, 0.263, 1.000)</color>
    </DiningChair>
    <Shelf>
      <position>(22, 0, 6)</position>
      <relativeRotation>Counterclockwise</relativeRotation>
      <stuff>WoodLog</stuff>
      <hp>65</hp>
      <color>RGBA(0.522, 0.380, 0.263, 1.000)</color>
    </Shelf>
    <Meat_Cougar>
      <rects>
        <li>(22,6,22,6)</li>
      </rects>
      <hp>60</hp>
      <stackCount>8</stackCount>
    </Meat_Cougar>
    <MealLavish>
      <rects>
        <li>(22,6,22,6)</li>
      </rects>
      <hp>50</hp>
      <stackCount>5</stackCount>
    </MealLavish>
    <Meat_Cassowary>
      <rects>
        <li>(22,6,22,6)</li>
      </rects>
      <hp>60</hp>
      <stackCount>24</stackCount>
    </Meat_Cassowary>
    <TorchWallLamp>
      <rects>
        <li>(8,7,8,7)</li>
        <li>(8,12,8,12)</li>
      </rects>
      <relativeRotation>Clockwise</relativeRotation>
      <hp>50</hp>
    </TorchWallLamp>
    <TorchWallLamp>
      <rects>
        <li>(10,7,10,7)</li>
        <li>(16,7,16,7)</li>
        <li>(10,12,10,12)</li>
        <li>(16,12,16,12)</li>
      </rects>
      <relativeRotation>Counterclockwise</relativeRotation>
      <hp>50</hp>
    </TorchWallLamp>
    <TableSculpting>
      <position>(11, 0, 7)</position>
      <relativeRotation>Opposite</relativeRotation>
      <stuff>WoodLog</stuff>
      <hp>117</hp>
      <color>RGBA(0.522, 0.380, 0.263, 1.000)</color>
    </TableSculpting>
    <RawRice>
      <rects>
        <li>(22,7,22,7)</li>
      </rects>
      <hp>57</hp>
      <stackCount>8</stackCount>
    </RawRice>
    <DiningChair>
      <rects>
        <li>(6,8,7,8)</li>
      </rects>
      <relativeRotation>Opposite</relativeRotation>
      <stuff>WoodLog</stuff>
      <quality>Excellent</quality>
      <hp>65</hp>
      <color>RGBA(0.522, 0.380, 0.263, 1.000)</color>
    </DiningChair>
    <Filth_Trash>
      <rects>
        <li>(13,8,13,8)</li>
        <li>(2,9,2,9)</li>
        <li>(7,9,7,9)</li>
        <li>(9,9,9,9)</li>
      </rects>
    </Filth_Trash>
    <Door>
      <rects>
        <li>(0,9,0,9)</li>
      </rects>
      <relativeRotation>Clockwise</relativeRotation>
      <stuff>FT_BlocksConcrete</stuff>
      <hp>320</hp>
      <color>RGBA(0.588, 0.588, 0.588, 1.000)</color>
    </Door>
    <Door>
      <rects>
        <li>(3,9,3,9)</li>
        <li>(23,9,23,9)</li>
        <li>(26,9,26,9)</li>
      </rects>
      <relativeRotation>Clockwise</relativeRotation>
      <stuff>Steel</stuff>
      <hp>160</hp>
      <color>RGBA(0.412, 0.412, 0.412, 1.000)</color>
    </Door>
    <Door>
      <rects>
        <li>(9,9,9,9)</li>
        <li>(15,9,15,9)</li>
      </rects>
      <relativeRotation>Clockwise</relativeRotation>
      <stuff>WoodLog</stuff>
      <hp>104</hp>
      <color>RGBA(0.522, 0.380, 0.263, 1.000)</color>
    </Door>
    <Door>
      <rects>
        <li>(6,10,6,10)</li>
        <li>(12,10,12,10)</li>
        <li>(19,10,19,10)</li>
        <li>(4,13,4,13)</li>
        <li>(6,13,6,13)</li>
        <li>(8,13,8,13)</li>
      </rects>
      <stuff>WoodLog</stuff>
      <hp>104</hp>
      <color>RGBA(0.522, 0.380, 0.263, 1.000)</color>
    </Door>
    <AnimalSleepingSpot>
      <rects>
        <li>(5,12,5,12)</li>
        <li>(7,12,7,12)</li>
      </rects>
      <color>RGBA(0.631, 0.835, 0.706, 1.000)</color>
    </AnimalSleepingSpot>
    <MeditationSpot>
      <rects>
        <li>(10,12,10,12)</li>
      </rects>
    </MeditationSpot>
    <Mote_PsyfocusPulse>
      <rects>
        <li>(10,12,10,12)</li>
      </rects>
    </Mote_PsyfocusPulse>
    <ComponentIndustrial>
      <rects>
        <li>(16,12,16,12)</li>
      </rects>
      <hp>63</hp>
      <stackCount>24</stackCount>
    </ComponentIndustrial>
    <FT_BlocksConcrete>
      <rects>
        <li>(16,12,17,13)</li>
      </rects>
      <stackCount>75</stackCount>
    </FT_BlocksConcrete>
    <Shelf>
      <positions>
        <li>(17, 0, 12)</li>
        <li>(20, 0, 12)</li>
        <li>(22, 0, 12)</li>
        <li>(17, 0, 13)</li>
        <li>(20, 0, 13)</li>
        <li>(22, 0, 13)</li>
        <li>(17, 0, 14)</li>
        <li>(20, 0, 14)</li>
        <li>(22, 0, 14)</li>
        <li>(17, 0, 15)</li>
        <li>(20, 0, 15)</li>
        <li>(22, 0, 15)</li>
      </positions>
      <relativeRotation>Opposite</relativeRotation>
      <stuff>WoodLog</stuff>
      <hp>65</hp>
      <color>RGBA(0.522, 0.380, 0.263, 1.000)</color>
    </Shelf>
    <PassiveCooler>
      <rects>
        <li>(18,12,18,12)</li>
        <li>(18,15,18,15)</li>
      </rects>
      <hp>80</hp>
    </PassiveCooler>
    <Silver>
      <rects>
        <li>(19,12,19,12)</li>
      </rects>
      <stackCount>500</stackCount>
    </Silver>
    <Silver>
      <rects>
        <li>(19,12,19,12)</li>
      </rects>
      <stackCount>110</stackCount>
    </Silver>
    <Leather_Pig>
      <rects>
        <li>(19,12,19,12)</li>
      </rects>
      <hp>59</hp>
      <stackCount>22</stackCount>
      <color>RGBA(0.682, 0.588, 0.494, 1.000)</color>
    </Leather_Pig>
    <SmokeleafJoint>
      <rects>
        <li>(20,12,20,12)</li>
      </rects>
      <hp>46</hp>
      <stackCount>2</stackCount>
    </SmokeleafJoint>
    <Leather_Panthera>
      <rects>
        <li>(20,12,20,12)</li>
      </rects>
      <hp>60</hp>
      <stackCount>21</stackCount>
      <color>RGBA(0.235, 0.235, 0.235, 1.000)</color>
    </Leather_Panthera>
    <Leather_Plain>
      <rects>
        <li>(20,12,20,12)</li>
      </rects>
      <hp>60</hp>
      <stackCount>57</stackCount>
      <color>RGBA(0.635, 0.416, 0.224, 1.000)</color>
    </Leather_Plain>
    <Leather_Light>
      <rects>
        <li>(21,12,21,12)</li>
      </rects>
      <hp>60</hp>
      <stackCount>54</stackCount>
      <color>RGBA(0.549, 0.333, 0.141, 1.000)</color>
    </Leather_Light>
    <Steel>
      <rects>
        <li>(21,12,22,15)</li>
        <li>(19,13,20,13)</li>
      </rects>
      <stackCount>75</stackCount>
    </Steel>
    <DiningChair>
      <rects>
        <li>(11,13,11,13)</li>
      </rects>
      <stuff>WoodLog</stuff>
      <quality>Poor</quality>
      <hp>65</hp>
      <color>RGBA(0.522, 0.380, 0.263, 1.000)</color>
    </DiningChair>
    <Gold>
      <rects>
        <li>(16,13,16,13)</li>
      </rects>
      <stackCount>49</stackCount>
    </Gold>
    <MedicineHerbal>
      <rects>
        <li>(16,13,16,13)</li>
      </rects>
      <hp>39</hp>
    </MedicineHerbal>
    <MedicineIndustrial>
      <rects>
        <li>(17,13,17,13)</li>
      </rects>
      <hp>54</hp>
      <stackCount>24</stackCount>
    </MedicineIndustrial>
    <MedicineIndustrial>
      <rects>
        <li>(17,13,17,13)</li>
      </rects>
      <hp>50</hp>
      <stackCount>12</stackCount>
    </MedicineIndustrial>
    <Apparel_Pants>
      <rects>
        <li>(19,13,19,13)</li>
      </rects>
      <stuff>Synthread</stuff>
      <quality>Normal</quality>
      <hp>124</hp>
    </Apparel_Pants>
    <Steel>
      <rects>
        <li>(19,13,19,13)</li>
      </rects>
      <stackCount>73</stackCount>
    </Steel>
    <Steel>
      <rects>
        <li>(20,13,20,13)</li>
      </rects>
      <stackCount>51</stackCount>
    </Steel>
    <WoodLog>
      <rects>
        <li>(21,13,21,13)</li>
      </rects>
      <hp>136</hp>
      <stackCount>49</stackCount>
    </WoodLog>
    <Apparel_Pants>
      <rects>
        <li>(21,13,21,13)</li>
      </rects>
      <stuff>Cloth</stuff>
      <quality>Poor</quality>
      <hp>4</hp>
    </Apparel_Pants>
    <ChunkGranite>
      <rects>
        <li>(24,13,24,13)</li>
        <li>(20,17,20,17)</li>
        <li>(19,18,19,18)</li>
        <li>(19,20,19,20)</li>
        <li>(21,20,21,20)</li>
      </rects>
      <hp>300</hp>
      <color>RGBA(0.412, 0.373, 0.380, 1.000)</color>
    </ChunkGranite>
    <Bed>
      <position>(4, 0, 15)</position>
      <relativeRotation>Opposite</relativeRotation>
      <stuff>WoodLog</stuff>
      <quality>Excellent</quality>
      <hp>91</hp>
      <color>RGBA(0.522, 0.380, 0.263, 1.000)</color>
    </Bed>
    <Bed>
      <positions>
        <li>(6, 0, 15)</li>
        <li>(8, 0, 15)</li>
      </positions>
      <relativeRotation>Opposite</relativeRotation>
      <stuff>WoodLog</stuff>
      <quality>Good</quality>
      <hp>91</hp>
      <color>RGBA(0.522, 0.380, 0.263, 1.000)</color>
    </Bed>
    <SimpleResearchBench>
      <position>(11, 0, 14)</position>
      <stuff>WoodLog</stuff>
      <hp>162</hp>
      <color>RGBA(0.522, 0.380, 0.263, 1.000)</color>
    </SimpleResearchBench>
    <FT_BlocksConcrete>
      <rects>
        <li>(16,14,16,14)</li>
      </rects>
      <stackCount>50</stackCount>
    </FT_BlocksConcrete>
    <WoodLog>
      <rects>
        <li>(16,14,16,14)</li>
      </rects>
      <hp>139</hp>
      <stackCount>59</stackCount>
    </WoodLog>
    <Dye>
      <rects>
        <li>(16,14,16,14)</li>
      </rects>
      <hp>48</hp>
    </Dye>
    <WoodLog>
      <rects>
        <li>(22,14,22,14)</li>
      </rects>
      <hp>144</hp>
      <stackCount>75</stackCount>
    </WoodLog>
    <ChunkGranite>
      <rects>
        <li>(24,14,24,14)</li>
        <li>(20,18,20,18)</li>
      </rects>
      <relativeRotation>Opposite</relativeRotation>
      <hp>300</hp>
      <color>RGBA(0.412, 0.373, 0.380, 1.000)</color>
    </ChunkGranite>
    <WoodLog>
      <rects>
        <li>(16,15,16,15)</li>
      </rects>
      <hp>148</hp>
      <stackCount>55</stackCount>
    </WoodLog>
    <ChunkGranite>
      <rects>
        <li>(21,17,22,17)</li>
      </rects>
      <relativeRotation>Counterclockwise</relativeRotation>
      <hp>300</hp>
      <color>RGBA(0.412, 0.373, 0.380, 1.000)</color>
    </ChunkGranite>
    <ChunkSandstone>
      <rects>
        <li>(22,18,22,18)</li>
      </rects>
      <relativeRotation>Counterclockwise</relativeRotation>
      <hp>300</hp>
      <color>RGBA(0.494, 0.408, 0.369, 1.000)</color>
    </ChunkSandstone>
    <ChunkSandstone>
      <rects>
        <li>(23,18,23,18)</li>
      </rects>
      <relativeRotation>Opposite</relativeRotation>
      <hp>300</hp>
      <color>RGBA(0.494, 0.408, 0.369, 1.000)</color>
    </ChunkSandstone>
    <ChunkSandstone>
      <rects>
        <li>(22,20,22,20)</li>
      </rects>
      <hp>300</hp>
      <color>RGBA(0.494, 0.408, 0.369, 1.000)</color>
    </ChunkSandstone>
  </things>
  <terrain>
    <Gravel>
      <rects>
        <li>(0,0,1,0)</li>
        <li>(5,0,6,0)</li>
        <li>(25,0,26,0)</li>
        <li>(0,8,1,8)</li>
        <li>(3,8,3,8)</li>
        <li>(25,8,25,8)</li>
        <li>(26,12,26,17)</li>
        <li>(25,18,25,19)</li>
        <li>(24,19,24,20)</li>
        <li>(26,20,26,20)</li>
      </rects>
    </Gravel>
    <Sandstone_Rough>
      <rects>
        <li>(2,0,4,0)</li>
        <li>(26,18,26,19)</li>
      </rects>
    </Sandstone_Rough>
    <Soil>
      <rects>
        <li>(7,0,24,1)</li>
        <li>(0,1,6,1)</li>
        <li>(25,1,26,2)</li>
        <li>(0,2,1,2)</li>
        <li>(9,2,9,8)</li>
        <li>(0,3,0,7)</li>
        <li>(26,3,26,8)</li>
        <li>(3,4,8,4)</li>
        <li>(10,4,23,4)</li>
        <li>(3,5,3,7)</li>
        <li>(15,5,15,8)</li>
        <li>(23,5,23,8)</li>
        <li>(0,10,1,10)</li>
        <li>(3,10,5,10)</li>
        <li>(7,10,11,10)</li>
        <li>(13,10,18,10)</li>
        <li>(20,10,23,10)</li>
        <li>(25,10,26,10)</li>
        <li>(0,11,0,20)</li>
        <li>(3,11,3,16)</li>
        <li>(9,11,9,19)</li>
        <li>(15,11,15,16)</li>
        <li>(23,11,23,16)</li>
        <li>(26,11,26,11)</li>
        <li>(5,13,5,16)</li>
        <li>(7,13,7,16)</li>
        <li>(4,16,4,16)</li>
        <li>(6,16,6,16)</li>
        <li>(8,16,8,16)</li>
        <li>(10,16,14,16)</li>
        <li>(16,16,22,16)</li>
        <li>(1,18,1,20)</li>
        <li>(2,19,8,19)</li>
        <li>(10,19,23,19)</li>
        <li>(2,20,2,20)</li>
        <li>(4,20,4,20)</li>
        <li>(6,20,6,20)</li>
        <li>(8,20,8,20)</li>
        <li>(10,20,10,20)</li>
        <li>(12,20,12,20)</li>
        <li>(14,20,14,20)</li>
        <li>(16,20,16,20)</li>
        <li>(18,20,18,20)</li>
        <li>(20,20,20,20)</li>
        <li>(22,20,22,20)</li>
      </rects>
    </Soil>
    <Concrete>
      <rects>
        <li>(2,2,8,3)</li>
        <li>(10,2,24,3)</li>
        <li>(1,3,1,7)</li>
        <li>(25,3,25,7)</li>
        <li>(2,4,2,18)</li>
        <li>(24,4,24,18)</li>
        <li>(4,5,8,9)</li>
        <li>(10,5,14,9)</li>
        <li>(16,5,22,9)</li>
        <li>(0,9,1,9)</li>
        <li>(3,9,3,9)</li>
        <li>(9,9,9,9)</li>
        <li>(15,9,15,9)</li>
        <li>(23,9,23,9)</li>
        <li>(25,9,26,9)</li>
        <li>(6,10,6,15)</li>
        <li>(12,10,12,15)</li>
        <li>(19,10,19,15)</li>
        <li>(1,11,1,17)</li>
        <li>(4,11,5,12)</li>
        <li>(7,11,8,12)</li>
        <li>(10,11,11,15)</li>
        <li>(13,11,14,15)</li>
        <li>(16,11,18,15)</li>
        <li>(20,11,22,15)</li>
        <li>(25,11,25,17)</li>
        <li>(4,13,4,15)</li>
        <li>(8,13,8,15)</li>
        <li>(3,17,8,18)</li>
        <li>(10,17,23,18)</li>
      </rects>
    </Concrete>
    <ShallowFloodwater>
      <rects>
        <li>(3,20,3,20)</li>
        <li>(5,20,5,20)</li>
        <li>(7,20,7,20)</li>
        <li>(9,20,9,20)</li>
        <li>(11,20,11,20)</li>
        <li>(13,20,13,20)</li>
        <li>(15,20,15,20)</li>
        <li>(17,20,17,20)</li>
        <li>(19,20,19,20)</li>
        <li>(21,20,21,20)</li>
        <li>(23,20,23,20)</li>
        <li>(25,20,25,20)</li>
      </rects>
    </ShallowFloodwater>
  </terrain>
  <terrainLayers>
    <terrainLayerDetail layer="tempGrid">
      <ShallowFloodwater>
        <rects>
          <li>(3,20,3,20)</li>
          <li>(5,20,5,20)</li>
          <li>(7,20,7,20)</li>
          <li>(9,20,9,20)</li>
          <li>(11,20,11,20)</li>
          <li>(13,20,13,20)</li>
          <li>(15,20,15,20)</li>
          <li>(17,20,17,20)</li>
          <li>(19,20,19,20)</li>
          <li>(21,20,21,20)</li>
          <li>(23,20,23,20)</li>
          <li>(25,20,25,20)</li>
        </rects>
      </ShallowFloodwater>
    </terrainLayerDetail>
    <terrainLayerDetail layer="topGrid">
      <Gravel>
        <rects>
          <li>(0,0,1,0)</li>
          <li>(5,0,6,0)</li>
          <li>(25,0,26,0)</li>
          <li>(0,8,1,8)</li>
          <li>(3,8,3,8)</li>
          <li>(25,8,25,8)</li>
          <li>(26,12,26,17)</li>
          <li>(25,18,25,20)</li>
          <li>(24,19,24,20)</li>
          <li>(26,20,26,20)</li>
        </rects>
      </Gravel>
      <Sandstone_Rough>
        <rects>
          <li>(2,0,4,0)</li>
          <li>(26,18,26,19)</li>
        </rects>
      </Sandstone_Rough>
      <Soil>
        <rects>
          <li>(7,0,24,1)</li>
          <li>(0,1,6,1)</li>
          <li>(25,1,26,2)</li>
          <li>(0,2,1,2)</li>
          <li>(9,2,9,8)</li>
          <li>(0,3,0,7)</li>
          <li>(26,3,26,8)</li>
          <li>(3,4,8,4)</li>
          <li>(10,4,23,4)</li>
          <li>(3,5,3,7)</li>
          <li>(15,5,15,8)</li>
          <li>(23,5,23,8)</li>
          <li>(0,10,1,10)</li>
          <li>(3,10,5,10)</li>
          <li>(7,10,11,10)</li>
          <li>(13,10,18,10)</li>
          <li>(20,10,23,10)</li>
          <li>(25,10,26,10)</li>
          <li>(0,11,0,20)</li>
          <li>(3,11,3,16)</li>
          <li>(9,11,9,20)</li>
          <li>(15,11,15,16)</li>
          <li>(23,11,23,16)</li>
          <li>(26,11,26,11)</li>
          <li>(5,13,5,16)</li>
          <li>(7,13,7,16)</li>
          <li>(4,16,4,16)</li>
          <li>(6,16,6,16)</li>
          <li>(8,16,8,16)</li>
          <li>(10,16,14,16)</li>
          <li>(16,16,22,16)</li>
          <li>(1,18,1,20)</li>
          <li>(2,19,8,20)</li>
          <li>(10,19,23,20)</li>
        </rects>
      </Soil>
      <Concrete>
        <rects>
          <li>(2,2,8,3)</li>
          <li>(10,2,24,3)</li>
          <li>(1,3,1,7)</li>
          <li>(25,3,25,7)</li>
          <li>(2,4,2,18)</li>
          <li>(24,4,24,18)</li>
          <li>(4,5,8,9)</li>
          <li>(10,5,14,9)</li>
          <li>(16,5,22,9)</li>
          <li>(0,9,1,9)</li>
          <li>(3,9,3,9)</li>
          <li>(9,9,9,9)</li>
          <li>(15,9,15,9)</li>
          <li>(23,9,23,9)</li>
          <li>(25,9,26,9)</li>
          <li>(6,10,6,15)</li>
          <li>(12,10,12,15)</li>
          <li>(19,10,19,15)</li>
          <li>(1,11,1,17)</li>
          <li>(4,11,5,12)</li>
          <li>(7,11,8,12)</li>
          <li>(10,11,11,15)</li>
          <li>(13,11,14,15)</li>
          <li>(16,11,18,15)</li>
          <li>(20,11,22,15)</li>
          <li>(25,11,25,17)</li>
          <li>(4,13,4,15)</li>
          <li>(8,13,8,15)</li>
          <li>(3,17,8,18)</li>
          <li>(10,17,23,18)</li>
        </rects>
      </Concrete>
    </terrainLayerDetail>
    <terrainLayerDetail layer="underGrid">
      <Soil>
        <rects>
          <li>(2,2,8,3)</li>
          <li>(10,2,24,3)</li>
          <li>(1,3,1,7)</li>
          <li>(25,3,25,7)</li>
          <li>(2,4,2,7)</li>
          <li>(24,4,24,7)</li>
          <li>(4,5,8,7)</li>
          <li>(10,5,14,9)</li>
          <li>(16,5,22,9)</li>
          <li>(5,8,8,9)</li>
          <li>(2,9,4,9)</li>
          <li>(9,9,9,9)</li>
          <li>(15,9,15,9)</li>
          <li>(23,9,26,9)</li>
          <li>(2,10,2,18)</li>
          <li>(6,10,6,15)</li>
          <li>(12,10,12,15)</li>
          <li>(19,10,19,15)</li>
          <li>(24,10,24,15)</li>
          <li>(1,11,1,17)</li>
          <li>(4,11,5,12)</li>
          <li>(7,11,8,12)</li>
          <li>(10,11,11,15)</li>
          <li>(13,11,14,15)</li>
          <li>(16,11,18,15)</li>
          <li>(20,11,22,15)</li>
          <li>(25,11,25,14)</li>
          <li>(4,13,4,15)</li>
          <li>(8,13,8,15)</li>
          <li>(3,17,8,18)</li>
          <li>(10,17,24,18)</li>
        </rects>
      </Soil>
      <Gravel>
        <rects>
          <li>(2,8,2,8)</li>
          <li>(4,8,4,8)</li>
          <li>(24,8,24,8)</li>
          <li>(0,9,1,9)</li>
          <li>(25,15,25,17)</li>
          <li>(24,16,24,16)</li>
        </rects>
      </Gravel>
    </terrainLayerDetail>
  </terrainLayers>
  <roofs>
    <RoofConstructed>
      <rects>
        <li>(0,1,26,19)</li>
      </rects>
    </RoofConstructed>
    <PlayerRoofZone>
      <rects>
        <li>(0,1,26,19)</li>
      </rects>
    </PlayerRoofZone>
  </roofs>
  <pawns>
    <pawn>
      <name>公座狼 1</name>
      <position>(2, 0, 9)</position>
      <data><![CDATA[公座狼 1*Warg*垃圾海盗|PlayerColony*公座狼 1*18098178*-16944744*1***0*****FF-FF-FF-FF*FF-FF-FF-FF*-1*FF-FF-FF-FF*FF-FF-FF-FF*FF-FF-FF-FF***Gunshot|2|Body|0|1|-1|0|-1|:PorcupineQuill|0.5|Body|0|0|-1|-1|-1|:MissingBodyPart|0.5|Tail|1|0|-1|-1|-1|*******Kills|6:KillsHumanlikes|0:KillsAnimals|6:KillsMechanoids|0:PawnsDowned|1:PawnsDownedHumanlikes|0:PawnsDownedAnimals|1:PawnsDownedMechanoids|0:ShotsFired|0:Headshots|0:DamageDealt|241:DamageTaken|121:TimesInMentalState|1:TimesOnFire|0:FiresExtinguished|0:OperationsReceived|0:OperationsPerformed|0:TimesTendedTo|10:TimesTendedOther|0:PeopleCaptured|0:PrisonersRecruited|0:PrisonersChatted|0:AnimalsTamed|0:AnimalsSlaughtered|0:MealsCooked|0:ThingsConstructed|0:ThingsInstalled|0:ThingsRepaired|0:ThingsCrafted|0:ThingsHauled|0:PlantsSown|0:PlantsHarvested|0:CellsMined|0:MessesCleaned|0:ResearchPointsResearched|0:CorpsesBuried|0:NutritionEaten|5.7253:BodiesStripped|0:ThingsUninstalled|0:ThingsDeconstructed|0:ArtifactsActivated|0:ContainersOpened|0:SwitchesFlicked|0:TimeAsColonistOrColonyAnimal|335360:TimeAsQuestLodger|0:TimeAsPrisoner|0:TimeInBed|261520:TimeInBedForMedicalReasons|5600:TimeDowned|2160:TimeGettingFood|6240:TimeGettingJoy|0:TimeUnderRoof|322560:TimeDrafted|0:TimeOnFire|0:TimeInMentalState|240:TimeHauling|0:TimeHandlingAnimals|0:TimeFirefighting|0:TimeWardening|0:TimeHunting|5440:TimeConstructing|0:TimeTreatingAndFeeding|0:TimeResearching|0:TimeCleaning|0:TimeRepairing|0:TimeMining|0:TimeSowingAndHarvesting|0:TimeAsChildInColony|0:KillsEntities|0:PawnsDownedEntities|0*Food|0.6285592:Rest|0.9619999********0*0**FF-FF-FF-FF***[ludeon.rimworld|ludeon.rimworld.odyssey|Nals.FacialAnimation]*|||||********FF-FF-FF-FF***]]></data>
    </pawn>
    <pawn>
      <name>建造师</name>
      <position>(15, 0, 9)</position>
      <data><![CDATA[建造师*Colonist*垃圾海盗|PlayerColony*建造师?建造师?Oliver*156216710*-349835779*1*Male**0***Troubadour**49-42-3D-FF*FF-FF-FF-FF*-1*FF-EF-C9-FF*FF-EF-C9-FF*8E-48-76-FF*Shooting|0|0|12.5968|0:Melee|5|1|0|0:Construction|11|2|3088.733|-15.99999:Mining|0|0|0|0:Cooking|20|0|564.97|12.005:Plants|5|0|2624.948|13.80398:Animals|8|1|1700|0:Crafting|5|0|0|0:Artistic|2|0|0|0:Medicine|1|0|214.375|0:Social|4|0|64.40005|1.4:Intellectual|5|0|0|0*DrugDesire|2*AlcoholTolerance|0.008373365|||0|-1|-1|-1|:SmokeleafHigh|0.2766669|||0|-1|-1|-1|:SmokeleafTolerance|0.02664994|||0|-1|-1|-1|*WreckageExplorer93*FurnitureBuilder83*Firefighter|1:Patient|1:Doctor|0:PatientBedRest|1:BasicWorker|1:Warden|1:Handling|1:Cooking|2:Hunting|0:Construction|3:Growing|3:Mining|0:PlantCutting|3:Smithing|0:Tailoring|0:Art|3:Crafting|0:Hauling|4:Cleaning|3:Research|4:Childcare|1:DarkStudy|0:Fishing|4:HaulingUrgent|1:FinishingOff|3:Rescuing|1*MeleeWeapon_Knife|Plasteel|A0-B2-B5-FF|2|1|280*Apparel_CollarShirt|Synthread|AE-DB-E4-FF|2|1|129:Apparel_FlakPants||9E-9E-9E-FF|2|1|194:Apparel_AdvancedHelmet|Plasteel|A0-B2-B5-FF|2|1|332*MealSurvivalPack||FF-FF-FF-FF|0|1|50*Kills|0:KillsHumanlikes|0:KillsAnimals|0:KillsMechanoids|0:PawnsDowned|0:PawnsDownedHumanlikes|0:PawnsDownedAnimals|0:PawnsDownedMechanoids|0:ShotsFired|0:Headshots|0:DamageDealt|0:DamageTaken|0:TimesInMentalState|0:TimesOnFire|0:FiresExtinguished|0:OperationsReceived|0:OperationsPerformed|0:TimesTendedTo|0:TimesTendedOther|7:PeopleCaptured|0:PrisonersRecruited|0:PrisonersChatted|0:AnimalsTamed|1:AnimalsSlaughtered|0:MealsCooked|19:ThingsConstructed|516:ThingsInstalled|3:ThingsRepaired|0:ThingsCrafted|0:ThingsHauled|228:PlantsSown|160:PlantsHarvested|82:CellsMined|0:MessesCleaned|79:ResearchPointsResearched|0:CorpsesBuried|0:NutritionEaten|22.27999:BodiesStripped|0:ThingsUninstalled|0:ThingsDeconstructed|1:ArtifactsActivated|0:ContainersOpened|0:SwitchesFlicked|0:TimeAsColonistOrColonyAnimal|780400:TimeAsQuestLodger|0:TimeAsPrisoner|0:TimeInBed|208800:TimeInBedForMedicalReasons|0:TimeDowned|0:TimeGettingFood|30000:TimeGettingJoy|41920:TimeUnderRoof|297920:TimeDrafted|15280:TimeOnFire|0:TimeInMentalState|0:TimeHauling|126080:TimeHandlingAnimals|10880:TimeFirefighting|0:TimeWardening|0:TimeHunting|0:TimeConstructing|108160:TimeTreatingAndFeeding|12080:TimeResearching|0:TimeCleaning|4480:TimeRepairing|0:TimeMining|0:TimeSowingAndHarvesting|128640:TimeAsChildInColony|0:KillsEntities|0:PawnsDownedEntities|0*Mood|0.9911524:Food|0.1837988:Rest|0.3964986:Joy|0.8679991:Beauty|0.3926812:Comfort|0.5656016:Outdoors|0.9935999:DrugDesire|0.3727321:RoomSize|0.6759999*CrashedTogether|战斗师?战斗师?Bishop|0||1|25|783150:CrashedTogether|研究员?研究员?Rothaga|0||1|25|783150:Chitchat|研究员?研究员?Rothaga|0||0.8475|20.03108|150:Chitchat|战斗师?战斗师?Bishop|0||0.875|11.30974|41250:NewColonyHope||0||1|0|303000:AttendedParty||0||0.9494053|0|275700:SleptInHeat||0||1|0|31650:SleptInBedroom||0||1|0|31650:AteLavishMeal||0||1|0|30450:SoakingWet||0||1|0|1350*SmokeleafHigh||0||1|0|0:EnvironmentHot||-1||1|0|0:NeedJoy||4||1|0|0:NeedComfort||-1||1|0|0:DrugDesireFascination||0||1|0|0:Expectations||4||1|0|0:EnvironmentDark||-1||1|0|0:NeedRoomSize||2||1|0|0:NeedFood||0||1|0|0***NoBeard*NoTattoo_Face*NoTattoo_Body*0*0**FF-FF-FF-FF*Astropolitan*探索 3*[ludeon.rimworld|Nals.FacialAnimation]*HeadNormal|EyeWide|LidNormal|BrowNormal|MouthNormal|SkinNormal**Male_AverageNormal*Baseliner**Skin_Melanin3:Hair_MidBlack***8E-48-76-FF***]]></data>
    </pawn>
    <pawn>
      <name>暗精灵</name>
      <position>(7, 0, 12)</position>
      <data><![CDATA[暗精灵*Iguana*垃圾海盗|PlayerColony*暗精灵*35614665*-34461246*2***0*****FF-FF-FF-FF*FF-FF-FF-FF*-1*FF-FF-FF-FF*FF-FF-FF-FF*FF-FF-FF-FF**********Kills|0:KillsHumanlikes|0:KillsAnimals|0:KillsMechanoids|0:PawnsDowned|0:PawnsDownedHumanlikes|0:PawnsDownedAnimals|0:PawnsDownedMechanoids|0:ShotsFired|0:Headshots|0:DamageDealt|0:DamageTaken|0:TimesInMentalState|0:TimesOnFire|0:FiresExtinguished|0:OperationsReceived|0:OperationsPerformed|0:TimesTendedTo|0:TimesTendedOther|0:PeopleCaptured|0:PrisonersRecruited|0:PrisonersChatted|0:AnimalsTamed|0:AnimalsSlaughtered|0:MealsCooked|0:ThingsConstructed|0:ThingsInstalled|0:ThingsRepaired|0:ThingsCrafted|0:ThingsHauled|0:PlantsSown|0:PlantsHarvested|0:CellsMined|0:MessesCleaned|0:ResearchPointsResearched|0:CorpsesBuried|0:NutritionEaten|4.555698:BodiesStripped|0:ThingsUninstalled|0:ThingsDeconstructed|0:ArtifactsActivated|0:ContainersOpened|0:SwitchesFlicked|0:TimeAsColonistOrColonyAnimal|780960:TimeAsQuestLodger|0:TimeAsPrisoner|0:TimeInBed|144080:TimeInBedForMedicalReasons|0:TimeDowned|0:TimeGettingFood|8320:TimeGettingJoy|0:TimeUnderRoof|486560:TimeDrafted|0:TimeOnFire|0:TimeInMentalState|0:TimeHauling|0:TimeHandlingAnimals|0:TimeFirefighting|0:TimeWardening|0:TimeHunting|0:TimeConstructing|0:TimeTreatingAndFeeding|0:TimeResearching|0:TimeCleaning|0:TimeRepairing|0:TimeMining|0:TimeSowingAndHarvesting|0:TimeAsChildInColony|0:KillsEntities|0:PawnsDownedEntities|0*Food|0.2319943:Rest|0.9579637********0*0**FF-FF-FF-FF***[ludeon.rimworld|Nals.FacialAnimation]*|||||********FF-FF-FF-FF***]]></data>
    </pawn>
    <pawn>
      <name>战斗师</name>
      <position>(10, 0, 12)</position>
      <data><![CDATA[战斗师*Colonist*垃圾海盗|PlayerColony*战斗师?战斗师?Bishop*97563643*-2224010211*1*Male**0***Shaved**2E-2E-2E-FF*FF-FF-FF-FF*-1*F2-C7-8C-FF*F2-C7-8C-FF*D7-B8-9D-FF*Shooting|8|2|3034.465|0:Melee|3|0|1715|0:Construction|7|0|276.5412|0:Mining|11|2|6634.418|-15.79999:Cooking|3|0|210.21|0:Plants|4|0|2032.163|0:Animals|10|2|1814.712|-7.899995:Crafting|10|2|-390.3146|-7.899995:Artistic|0|0|0|0:Medicine|5|0|0|0:Social|2|0|83.29996|1.225:Intellectual|6|0|243.4462|78.03228*Delicate|0:TooSmart|0:QuickSleeper|0*SmokeleafTolerance|0.01952232|||0|-1|-1|-1|:PsychicAmplifier|1|Brain|15|0|1|-1|-1|*TechnicalKid1*NetworkEngineer34*Firefighter|1:Patient|1:Doctor|1:PatientBedRest|1:BasicWorker|1:Warden|0:Handling|1:Cooking|3:Hunting|4:Construction|4:Growing|4:Mining|3:PlantCutting|4:Smithing|4:Tailoring|4:Art|0:Crafting|2:Hauling|2:Cleaning|4:Research|4:Childcare|0:DarkStudy|4:Fishing|4:HaulingUrgent|1:FinishingOff|3:Rescuing|1*MeleeWeapon_Knife|Steel|69-69-69-FF|1|1|22*Apparel_CollarShirt|Synthread|AE-DB-E4-FF|2|1|128:Apparel_Pants|Synthread|AE-DB-E4-FF|2|1|129:Apparel_FlakVest||54-54-54-FF|2|1|189*Gun_BoltActionRifle||FF-FF-FF-FF|2|1|99:MealSurvivalPack||FF-FF-FF-FF|0|1|50*Kills|4:KillsHumanlikes|0:KillsAnimals|4:KillsMechanoids|0:PawnsDowned|0:PawnsDownedHumanlikes|0:PawnsDownedAnimals|0:PawnsDownedMechanoids|0:ShotsFired|10:Headshots|0:DamageDealt|206:DamageTaken|4:TimesInMentalState|0:TimesOnFire|0:FiresExtinguished|0:OperationsReceived|0:OperationsPerformed|0:TimesTendedTo|1:TimesTendedOther|0:PeopleCaptured|0:PrisonersRecruited|0:PrisonersChatted|0:AnimalsTamed|0:AnimalsSlaughtered|0:MealsCooked|0:ThingsConstructed|1:ThingsInstalled|16:ThingsRepaired|0:ThingsCrafted|0:ThingsHauled|187:PlantsSown|58:PlantsHarvested|18:CellsMined|124:MessesCleaned|60:ResearchPointsResearched|0:CorpsesBuried|0:NutritionEaten|23.2:BodiesStripped|1:ThingsUninstalled|0:ThingsDeconstructed|0:ArtifactsActivated|0:ContainersOpened|0:SwitchesFlicked|0:TimeAsColonistOrColonyAnimal|782320:TimeAsQuestLodger|0:TimeAsPrisoner|0:TimeInBed|164800:TimeInBedForMedicalReasons|5600:TimeDowned|0:TimeGettingFood|28640:TimeGettingJoy|61040:TimeUnderRoof|397200:TimeDrafted|18640:TimeOnFire|0:TimeInMentalState|0:TimeHauling|135600:TimeHandlingAnimals|5360:TimeFirefighting|0:TimeWardening|0:TimeHunting|0:TimeConstructing|1840:TimeTreatingAndFeeding|0:TimeResearching|0:TimeCleaning|3040:TimeRepairing|0:TimeMining|167360:TimeSowingAndHarvesting|47280:TimeAsChildInColony|0:KillsEntities|0:PawnsDownedEntities|0*Mood|0.98:Food|0.9399999:Rest|0.8479996:Joy|1:Beauty|0.2984083:Comfort|0.8016012:Outdoors|0.8855981:DrugDesire|0.5:RoomSize|0.5726923*CrashedTogether|建造师?建造师?Oliver|0||1|25|782400:CrashedTogether|研究员?研究员?Rothaga|0||1|25|782400:Chitchat|研究员?研究员?Rothaga|0||0.8475|3.5431|55050:Chitchat|建造师?建造师?Oliver|0||0.93|13.72968|40650:DeepTalk|研究员?研究员?Rothaga|0||0.8475|12.7125|558900:NewColonyHope||0||1|0|302250:DeepTalk|奥雷留斯?奥雷留斯?阿斯拜茨|0||1.314|19.71|284700:Slighted|研究员?研究员?Rothaga|0||0.8475|-4.2375|281700:Insulted|建造师?建造师?Oliver|0||0.93|-13.95|277650:GainedTitle||0|Yeoman|1|0|274650:DeepTalk|研究员?研究员?Rothaga|0||0.8475|12.7125|88950:AteLavishMeal||0||1|0|2250:SleptInHeat||0||1|0|9600:SleptInBedroom||0||1|0|9600*NeedFood||-1||1|0|0:NeedJoy||4||1|0|0:NeedComfort||3||1|0|0:NeedBeauty||2||1|0|0:Expectations||4||1|0|0**Yeoman*NoBeard*NoTattoo_Face*NoTattoo_Body*0*0.6223065*Stun*FF-FF-FF-FF*Astropolitan*探索 3*[ludeon.rimworld|ludeon.rimworld.royalty|ludeon.rimworld.biotech|Nals.FacialAnimation]*HeadNormal|EyePointy|LidNormal|BrowNormal|MouthNormal|SkinNormal**Male_NarrowNormal*Baseliner**Skin_Melanin6:Hair_DarkBlack***D7-B8-9D-FF***]]></data>
    </pawn>
    <pawn>
      <name>研究员</name>
      <position>(4, 0, 15)</position>
      <data><![CDATA[研究员*Colonist*垃圾海盗|PlayerColony*研究员?研究员?Rothaga*129731640*-150178208*1*Male**0***AFUhairM09**36-36-36-FF*FF-FF-FF-FF*-1*82-5B-30-FF*82-5B-30-FF*BA-4A-7C-FF*Shooting|9|2|4489.418|0:Melee|2|0|0|0:Construction|6|1|3859.526|0:Mining|1|0|0|0:Cooking|0|0|0|0:Plants|5|0|2386.31|51.76507:Animals|3|0|0|0:Crafting|5|1|0|0:Artistic|0|0|0|0:Medicine|6|1|612.5|0:Social|1|0|56.00003|0.7:Intellectual|9|2|9288.961|0*DislikesWomen|0:Beauty|1*SmokeleafTolerance|0.0229382|||0|-1|-1|-1|*StudentEngineer34*EngineeredPilot75*Firefighter|1:Patient|1:Doctor|1:PatientBedRest|1:BasicWorker|1:Warden|0:Handling|0:Cooking|0:Hunting|3:Construction|4:Growing|3:Mining|4:PlantCutting|3:Smithing|4:Tailoring|4:Art|4:Crafting|3:Hauling|0:Cleaning|0:Research|2:Childcare|0:DarkStudy|2:Fishing|4:HaulingUrgent|0:FinishingOff|3:Rescuing|1*Gun_Revolver||FF-FF-FF-FF|2|1|100*Apparel_CollarShirt|Synthread|AE-DB-E4-FF|2|1|125:Apparel_Pants|Synthread|AE-DB-E4-FF|2|1|124:AM_LassoDevilstrand||B4-3C-3C-FF|0|1|12**Kills|1:KillsHumanlikes|1:KillsAnimals|0:KillsMechanoids|0:PawnsDowned|1:PawnsDownedHumanlikes|0:PawnsDownedAnimals|1:PawnsDownedMechanoids|0:ShotsFired|10:Headshots|0:DamageDealt|96:DamageTaken|0:TimesInMentalState|0:TimesOnFire|0:FiresExtinguished|0:OperationsReceived|0:OperationsPerformed|0:TimesTendedTo|0:TimesTendedOther|4:PeopleCaptured|0:PrisonersRecruited|0:PrisonersChatted|0:AnimalsTamed|0:AnimalsSlaughtered|0:MealsCooked|0:ThingsConstructed|144:ThingsInstalled|1:ThingsRepaired|0:ThingsCrafted|0:ThingsHauled|47:PlantsSown|230:PlantsHarvested|126:CellsMined|0:MessesCleaned|0:ResearchPointsResearched|505.7109:CorpsesBuried|0:NutritionEaten|22.1:BodiesStripped|0:ThingsUninstalled|0:ThingsDeconstructed|1:ArtifactsActivated|0:ContainersOpened|0:SwitchesFlicked|0:TimeAsColonistOrColonyAnimal|780480:TimeAsQuestLodger|0:TimeAsPrisoner|0:TimeInBed|213520:TimeInBedForMedicalReasons|0:TimeDowned|0:TimeGettingFood|31680:TimeGettingJoy|38160:TimeUnderRoof|329920:TimeDrafted|14560:TimeOnFire|0:TimeInMentalState|0:TimeHauling|43440:TimeHandlingAnimals|0:TimeFirefighting|0:TimeWardening|0:TimeHunting|0:TimeConstructing|53520:TimeTreatingAndFeeding|6240:TimeResearching|72320:TimeCleaning|0:TimeRepairing|0:TimeMining|0:TimeSowingAndHarvesting|118880:TimeAsChildInColony|0:KillsEntities|0:PawnsDownedEntities|0*Mood|0.7415992:Food|0.1955971:Rest|0.8085957:Joy|0.6405556:Beauty|0.420342:Comfort|0.93:Outdoors|0.9976:DrugDesire|0.5:RoomSize|0.8379999*CrashedTogether|战斗师?战斗师?Bishop|0||1|25|782400:CrashedTogether|建造师?建造师?Oliver|0||1|25|782400:Chitchat|建造师?建造师?Oliver|0||0.93|24.39188|59400:Chitchat|战斗师?战斗师?Bishop|0||0.875|3.057567|54900:DeepTalk|战斗师?战斗师?Bishop|0||0.875|13.125|559200:NewColonyHope||0||1|0|302250:HonorableBestowingCeremony||0||1|0|274950:DeepTalk|战斗师?战斗师?Bishop|0||0.6677632|10.01645|89250:AteLavishMeal||0||1|0|28500:AteWithoutTable||0||1|0|28500:SleptInHeat||0||1|0|6750:SleptInBedroom||0||1|0|6750*SmokeleafHigh||-1||1|0|0:NeedJoy||-1||1|0|0:NeedComfort||4||1|0|0:Expectations||4||1|0|0:EnvironmentDark||-1||1|0|0:EnvironmentHot||-1||1|0|0:NeedRoomSize||-1||1|0|0:NeedRest||-1||1|0|0:NeedFood||0||1|0|0*Spouse|Afeeba?Feeb?Dafo|0**NoBeard*NoTattoo_Face*NoTattoo_Body*0*0**FF-FF-FF-FF*Astropolitan*探索 3*[ludeon.rimworld|jintuzilamian.hairstyle.afumenshairstyles|co.uk.epicguru.meleeanimation|ludeon.rimworld.royalty|Nals.FacialAnimation]*HeadNormal|EyePointy|LidNormal|BrowNormal|MouthNormal|SkinNormal**Male_AverageWide*Baseliner**Skin_Melanin8:Hair_DarkBlack***BA-4A-7C-FF***]]></data>
    </pawn>
  </pawns>
</PrefabDef>