<PrefabDef>
  <defName>Prefab_20260103_235456</defName>
  <size>(10,6)</size>
  <extraInfo>
    <version>1.6.9438.37837</version>
    <name>RENT 2</name>
    <description></description>
    <tags></tags>
    <author>ME</author>
    <category>Dormitory</category>
    <BuildingID>9eda1594-2c89-43b0-9256-0662f20388c0</BuildingID>
    <modPackages></modPackages>
    <multiLanguage>
      <name>
        <default>RENT 2</default>
        <en>RENT 2</en>
      </name>
    </multiLanguage>
  </extraInfo>
  <things>
    <Wall>
      <rects>
        <li>(0,0,4,0)</li>
        <li>(6,0,9,0)</li>
        <li>(0,1,0,5)</li>
        <li>(9,1,9,5)</li>
        <li>(1,5,8,5)</li>
      </rects>
      <stuff>WoodLog</stuff>
      <hp>195</hp>
      <color>RGBA(0.522, 0.380, 0.263, 1.000)</color>
    </Wall>
    <Door>
      <rects>
        <li>(5,0,5,0)</li>
      </rects>
      <stuff>WoodLog</stuff>
      <hp>104</hp>
      <color>RGBA(0.522, 0.380, 0.263, 1.000)</color>
    </Door>
  </things>
  <terrainLayers></terrainLayers>
  <roofs>
    <RoofConstructed>
      <rects>
        <li>(0,0,0,5)</li>
        <li>(7,0,9,0)</li>
        <li>(3,2,3,5)</li>
        <li>(5,2,5,5)</li>
        <li>(4,3,4,5)</li>
        <li>(2,4,2,5)</li>
        <li>(6,4,6,5)</li>
      </rects>
    </RoofConstructed>
    <PlayerRoofZone>
      <rects>
        <li>(0,0,9,5)</li>
      </rects>
    </PlayerRoofZone>
  </roofs>
</PrefabDef>